jupyter_sshd_proxy/__init__.py
jupyter_sshd_proxy-0.3.0.dist-info/LICENSE
jupyter_sshd_proxy-0.3.0.dist-info/METADATA
jupyter_sshd_proxy-0.3.0.dist-info/WHEEL
jupyter_sshd_proxy-0.3.0.dist-info/entry_points.txt
jupyter_sshd_proxy-0.3.0.dist-info/top_level.txt
jupyter_sshd_proxy-0.3.0.dist-info/RECORD
