Metadata-Version: 2.1
Name: jupyter-sshd-proxy
Version: 0.3.0
Summary: Run sshd under jupyter
Home-page: https://github.com/yuvipanda/jupyter-sshd-proxy
Author: Yuvi Panda
Classifier: Framework :: Jupyter
License-File: LICENSE
Requires-Dist: jupyter-server-proxy >=4.3.0
